<?xml version="1.0" encoding="UTF-8"?>

<phrasebook>


    <sentence desc="What is somebody's name?" id="QWhatName">
        <node syntax="PQuestion">
            <node desc="Who are we talking about?" syntax="QWhatName">
                <node child="allpersons" />
            </node>
        </node>
    </sentence>

    <sentence desc="Somebody's name is..." id="AHasName">
        <node child="phraseit">
            <node syntax="PropAction">
                <node syntax="AHasName">
                   <node child="allpersons">
                       <node syntax="NameNN"/>
                   </node>
                </node>
            </node>
        </node>
    </sentence>

    <sentence desc="How old is someone?" id="QWhatAge">
        <node syntax="PQuestion">
            <node syntax="QWhatAge">
                <node child="allpersons" />
            </node>
        </node>
    </sentence>

    <sentence desc="Someone's age is..." id="AHasAge">
        <node syntax="PQuestion">
            <node syntax="QProp">
                <node syntax="PropAction">
                    <node syntax="NNumeral">
                        <node syntax="AHasAge">
                            <node child="allpersons" />
                        </node>
                    </node>
                </node>
            </node>
        </node>
    </sentence>

    <sentence desc="Someone loves someone" id="ALove">
        <node child="phraseit">
            <node syntax="PropAction">
                <node syntax="ALove">
                    <option option="Who loves someone?">
                        <node child="allpersons"></node>
                    </option>
                    <option option="Who is loved?">
                        <node child="allpersons"></node>
                    </option>
                </node>
            </node>
        </node>
    </sentence>

    <sentence desc="Someone is married" id="AMarried">
        <node child="phraseit">
            <node syntax="PropAction">
                <node syntax="AMarried">
                    <node child="allpersons" />
                </node>
            </node>
        </node>
    </sentence>

    <sentence desc="Someone is scared" id="AScared">
        <node syntax="Psentence">
            <node child="phraseit">
                <node child="allpersons"></node>
            </node>
        </node>
    </sentence>

    <sentence desc="How far is something?" id="HowFar">
        <node syntax="PQuestion">
            <node syntax="HowFar">
                <node child="superlative_places" />
            </node>
        </node>
    </sentence>


    <!--Option lists -->
    <child id="allpersons">
            <node child="persons" />
            <node child="familypersons" />
    </child>

    <child id="superlative_places">
        <option option="What place are we asking about?">
            <node child="superlative"></node>
            <node child="places"></node>
        </option>
    </child>

    <child id="phraseit">
        <option option="How do you want to phrase it?">
            <node desc="statement" syntax="PSentence">
                <node syntax="SProp"></node>
            </node>
            <node desc="question" syntax="PQuestion">
                <node syntax="QProp"></node>
            </node>
            <node desc="negation" syntax="PSentence">
                <node syntax="SPropNot"></node>
            </node>
        </option>
    </child>

    <child id="nationality">
        <option option="What nationality">
            <node desc="Belgian" syntax="Belgian"></node>
            <node desc="Bulgarian" syntax="CitiNat Bulgarian"></node>
            <node desc="Catalan" syntax="CitiNat Catalan"></node>
            <node desc="Dutch" syntax="CitiNat Dutch"></node>
            <node desc="Danish" syntax="CitiNat Danish"></node>
            <node desc="English" syntax="CitiNat English"></node>
            <node desc="Finnish" syntax="CitiNat Finnish"></node>
            <node desc="French" syntax="CitiNat French"></node>
            <node desc="German" syntax="CitiNat German"></node>
            <node desc="Italian" syntax="CitiNat Italian"></node>
            <node desc="Norwegian" syntax="CitiNat Norwegian"></node>
            <node desc="Polish" syntax="CitiNat Polish"></node>
            <node desc="Romanian" syntax="CitiNat Romanian"></node>
            <node desc="Russian" syntax="CitiNat Russian"></node>
            <node desc="Spanish" syntax="CitiNat Spanish"></node>
            <node desc="Swedish" syntax="CitiNat Swedish"></node>
        </option>
    </child>

    <child id="places">
        <option option="What place are we asking about?">
            <node desc="supermarket" syntax="Supermarket"></node>
            <node desc="bank" syntax="Bank"></node>
            <node desc="amusment park" syntax="AmusmentPark"></node>
            <node desc="bar" syntax="Bar"></node>
            <node desc="Cafeteria" syntax="Cafeteria"></node>
            <node desc="car park" syntax="Parking"></node>
            <node desc="center" syntax="Center"></node>
            <node desc="cinema" syntax="Cinema"></node>
            <node desc="church" syntax="Church"></node>
            <node desc="disco" syntax="Disco"></node>
            <node desc="hospital" syntax="Hospital"></node>
            <node desc="hotel" syntax="Hotel"></node>
            <node desc="museum" syntax="Museum"></node>
            <node desc="park" syntax="Park"></node>
            <node desc="pharmacy" syntax="Pharmacy"></node>
            <node desc="post office" syntax="PostOffice"></node>
            <node desc="pub" syntax="Pub"></node>
            <node desc="restaurant" syntax="CitRestaurant">
                <node child="nationality"></node>
            </node>
            <node desc="school" syntax="School"></node>
            <node desc="shop" syntax="Shop"></node>
        </option>
    </child>

    <child id="superlative">
        <option option="Superlative">
            <node desc="(no superlative)" syntax="ThePlace"></node>
            <node desc="best" syntax="SuperIPlace TheBest"></node>
            <node desc="worst" syntax="SuperIPlace TheWorst"></node>
            <node desc="nearest" syntax="SuperIPlace TheClosest"></node>
            <node desc="cheapest" syntax="SuperIPlace TheCheapest"></node>
            <node desc="most expensive" syntax="SuperIPlace TheMostExpensive"></node>
            <node desc="most popular" syntax="SuperIPlace TheMostPopular"></node>
        </option>
    </child>

    <child id="persons">
        <node desc="me (male)" syntax="IMale" />
        <node desc="me (female)" syntax="IFemale" />
        <node desc="you (a male friend)" syntax="YouFamMale" />
        <node desc="you (a female friend)" syntax="YouFamFemale" />
        <node desc="you (a male stranger)" syntax="YouPolMale" />
        <node desc="you (a female stranger)" syntax="YouPolFemale" />
    </child>

    <child id="familypersons">
        <node desc="Wife of..." syntax="Wife">
            <option option="">
                <node child="persons" />
            </option>
        </node>
        <node desc="Husband of..." syntax="Husband">
            <option option="">
                <node child="persons" />
            </option>
        </node>
        <node desc="Daughter of..." syntax="Daughter">
            <option option="">
                <node child="persons" />
            </option>
        </node>
        <node desc="Son of..." syntax="Son">
            <option option="">
                <node child="persons" />
            </option>
        </node>
        <node desc="Children of..." syntax="Children">
            <option option="">
                <node child="persons" />
            </option>
        </node>
    </child>

</phrasebook>

